{
      "type": "BurstTurret",
      "name": "Shotgunner",
      "description": "Shoots bullets like crazy.",
      "health": 600,
      "size": 1,
      "reload": 70,
      "width": 2,
      "shots": 20,
      "burstSpacing": 0,
      "range": 50,
      "ammoUseEffect": "shellEjectSmall",
      "inaccuracy": 30,
      "rotatespeed": 10,
      "ammo": {
          "copper": "standardCopper",
          "graphite": "standardDense",
          "silicon": "standardHoming",
          "pyratite": "standardIncendiary",
        },
      "requirements": [
        { "item": "graphite", "amount": 80},
        { "item": "copper", "amount": 350},
        { "item": "titanium", "amount": 80}
      ],
      "category": "turret",
      "research": "repeater"
}
